MANIFEST.in
README.rst
setup.py
aliyunsdkcdn/__init__.py
aliyunsdkcdn/request/__init__.py
aliyunsdkcdn/request/v20141111/AddCdnDomainRequest.py
aliyunsdkcdn/request/v20141111/AddFCTriggerRequest.py
aliyunsdkcdn/request/v20141111/AddLiveAppRecordConfigRequest.py
aliyunsdkcdn/request/v20141111/AddLiveAppSnapshotConfigRequest.py
aliyunsdkcdn/request/v20141111/AddLiveDomainMappingRequest.py
aliyunsdkcdn/request/v20141111/AddLivePullStreamInfoRequest.py
aliyunsdkcdn/request/v20141111/AddLiveStreamTranscodeRequest.py
aliyunsdkcdn/request/v20141111/BatchDescribeDomainBpsDataRequest.py
aliyunsdkcdn/request/v20141111/ClearUserBlackListRequest.py
aliyunsdkcdn/request/v20141111/ClearUserDomainBlackListRequest.py
aliyunsdkcdn/request/v20141111/CreateLiveStreamRecordIndexFilesRequest.py
aliyunsdkcdn/request/v20141111/DeleteCacheExpiredConfigRequest.py
aliyunsdkcdn/request/v20141111/DeleteCdnDomainRequest.py
aliyunsdkcdn/request/v20141111/DeleteFCTriggerRequest.py
aliyunsdkcdn/request/v20141111/DeleteHttpHeaderConfigRequest.py
aliyunsdkcdn/request/v20141111/DeleteLiveAppRecordConfigRequest.py
aliyunsdkcdn/request/v20141111/DeleteLiveAppSnapshotConfigRequest.py
aliyunsdkcdn/request/v20141111/DeleteLiveDomainMappingRequest.py
aliyunsdkcdn/request/v20141111/DeleteLivePullStreamInfoRequest.py
aliyunsdkcdn/request/v20141111/DeleteLiveStreamTranscodeRequest.py
aliyunsdkcdn/request/v20141111/DescribeCdnDomainBaseDetailRequest.py
aliyunsdkcdn/request/v20141111/DescribeCdnDomainConfigsRequest.py
aliyunsdkcdn/request/v20141111/DescribeCdnDomainDetailRequest.py
aliyunsdkcdn/request/v20141111/DescribeCdnDomainLogsRequest.py
aliyunsdkcdn/request/v20141111/DescribeCdnMonitorDataRequest.py
aliyunsdkcdn/request/v20141111/DescribeCdnRegionAndIspRequest.py
aliyunsdkcdn/request/v20141111/DescribeCdnServiceRequest.py
aliyunsdkcdn/request/v20141111/DescribeCdnTypesRequest.py
aliyunsdkcdn/request/v20141111/DescribeCustomLogConfigRequest.py
dd_aliyun_python_sdk_cdn.egg-info/PKG-INFO
dd_aliyun_python_sdk_cdn.egg-info/SOURCES.txt
dd_aliyun_python_sdk_cdn.egg-info/dependency_links.txt
dd_aliyun_python_sdk_cdn.egg-info/requires.txt
dd_aliyun_python_sdk_cdn.egg-info/top_level.txt